pyptly/__init__.py
pyptly/api.py
pyptly/utils.py
pyptly-1.0.2.dist-info/DESCRIPTION.rst
pyptly-1.0.2.dist-info/METADATA
pyptly-1.0.2.dist-info/RECORD
pyptly-1.0.2.dist-info/WHEEL
pyptly-1.0.2.dist-info/metadata.json
pyptly-1.0.2.dist-info/top_level.txt
pyptly-1.0.2.dist-info/zip-safe
tests/__init__.py
tests/conf.py
tests/test_api.py
tests/test_utils.py
